pytoo/__init__.py
pytoo/hello.py
pytoo-0.1.2.dist-info/LICENSE
pytoo-0.1.2.dist-info/WHEEL
pytoo-0.1.2.dist-info/METADATA
pytoo-0.1.2.dist-info/RECORD
