Metadata-Version: 2.1
Name: pytoo
Version: 0.1.2
Summary: Example Python Library
Author: Juraj Figura
Author-email: guitarist90@gmail.com
Requires-Python: >=3.7,<4.0
Classifier: Programming Language :: Python :: 3
Classifier: Programming Language :: Python :: 3.10
Classifier: Programming Language :: Python :: 3.7
Classifier: Programming Language :: Python :: 3.8
Classifier: Programming Language :: Python :: 3.9
